taar/__init__.py
taar/context.py
taar/flask_app.py
taar/plugin.py
taar/profile_fetcher.py
taar/adapters/__init__.py
taar/adapters/tests/__init__.py
taar/recommenders/__init__.py
taar/recommenders/base_recommender.py
taar/recommenders/collaborative_recommender.py
taar/recommenders/ensemble_recommender.py
taar/recommenders/hybrid_recommender.py
taar/recommenders/lazys3.py
taar/recommenders/locale_recommender.py
taar/recommenders/recommendation_manager.py
taar/recommenders/s3config.py
taar/recommenders/similarity_recommender.py
taar/tests/__init__.py
mozilla_taar3-0.4.6.dist-info/LICENSE
mozilla_taar3-0.4.6.dist-info/METADATA
mozilla_taar3-0.4.6.dist-info/WHEEL
mozilla_taar3-0.4.6.dist-info/entry_points.txt
mozilla_taar3-0.4.6.dist-info/top_level.txt
mozilla_taar3-0.4.6.dist-info/RECORD
